pbumysql/__init__.py
pbumysql/mysql_connection.py
pbumysql/mysql_store.py
pbumysql-0.1.0.dist-info/LICENSE
pbumysql-0.1.0.dist-info/METADATA
pbumysql-0.1.0.dist-info/WHEEL
pbumysql-0.1.0.dist-info/top_level.txt
pbumysql-0.1.0.dist-info/RECORD
