Metadata-Version: 2.1
Name: pbumysql
Version: 0.1.0
Summary: Basic MySQL wrapper for object-oriented collection handling
Home-page: https://github.com/ilfrich/pbu-mysql
Author: Peter Ilfrich
Author-email: das-peter@gmx.de
License: Apache-2.0
Platform: UNKNOWN
Requires-Dist: mysql-connector-python
Requires-Dist: tzlocal
Requires-Dist: pbu (>=1.0.0)
